{
  "date": "2026-05-16",
  "picks": [
    {
      "rank": 1,
      "match": "SC Freiburg vs RB Leipzig",
      "league": "Bundesliga - Germany",
      "kickoff": "2026-05-16T13:30:00Z",
      "pick": "Away",
      "pick_label": "RB Leipzig to win",
      "odds": 2.45,
      "implied_prob": 40.8,
      "our_prob": 48.0,
      "edge": 7.2,
      "kelly_fraction": 0.05,
      "reasoning": "Leipzig consistently finish strong and have superior squad depth compared to Freiburg. With rumors of new signings like Brajan Gruda, the team is looking forward with momentum, while Freiburg has struggled for consistency in the latter half of the season.",
      "confidence": "high",
      "result": null,
      "return": null,
      "settled": false
    },
    {
      "rank": 2,
      "match": "FC St. Pauli vs VfL Wolfsburg",
      "league": "Bundesliga - Germany",
      "kickoff": "2026-05-16T13:30:00Z",
      "pick": "Home",
      "pick_label": "FC St. Pauli to win",
      "odds": 2.75,
      "implied_prob": 36.4,
      "our_prob": 42.0,
      "edge": 5.6,
      "kelly_fraction": 0.016,
      "reasoning": "Wolfsburg are in a 'difficult and sad situation' with relegation threats looming large. FC St. Pauli, playing at their iconic Millerntor-Stadion, will look to finish their season with a statement win against a demoralized opponent.",
      "confidence": "medium",
      "result": null,
      "return": null,
      "settled": false
    },
    {
      "rank": 3,
      "match": "Eintracht Frankfurt vs VfB Stuttgart",
      "league": "Bundesliga - Germany",
      "kickoff": "2026-05-16T13:30:00Z",
      "pick": "Away",
      "pick_label": "VfB Stuttgart to win",
      "odds": 1.91,
      "implied_prob": 52.4,
      "our_prob": 58.0,
      "edge": 5.6,
      "kelly_fraction": 0.031,
      "reasoning": "Stuttgart have been one of the standout teams of the season. Their tactical fluidity and the clinical form of their front line make them favorites even away at Frankfurt, who have occasionally lacked defensive discipline in high-stakes matches.",
      "confidence": "high",
      "result": null,
      "return": null,
      "settled": false
    }
  ],
  "acca_available": true,
  "acca_odds": 12.87,
  "acca_result": null,
  "acca_return": null
}
